Workbook

Sheet Assumptions
A1: Workit — Cash Flow Assumptions
A2: Furthersky Solutions · Reg. 2024/163230/07 · workitsa.co.za
A3: All figures in South African Rand (R). Year 1 of operations (illustrative start Jul 2026).
A5: KEY FUNDING INPUTS
A6: Founder seed capital (opening cash) | B6: 5000 | C6: Own funds already in the business.
A7: Grant funding sought (Year 1) | B7: 250000 | C7: NYDA grant cap; also frames the Youth Challenge Fund / Pitch & Polish asks.
A8: Grant disbursement timing | B8: Month 1 | C8: Modelled as a single Month-1 inflow; adjust to the funder's tranche schedule.
A10: REVENUE ASSUMPTIONS
A11: Monetisation start | B11: Month 8 | C11: Free during launch (founder decision); a small service fee begins once liquidity is proven.
A12: Revenue model | B12: Service fee | C12: Light facilitation fee on confirmed jobs + optional worker 'verified boost'. Conservative ramp.
A13: Year-1 platform revenue (total) | B13: R36,500 | C13: Deliberately conservative — proves a revenue path, not the main Year-1 story.
A15: COST DRIVERS (monthly, unless one-off)
A16: Founder stipend | B16: 6000 | C16: Modest stipend — grant money goes to growth, not salary.
A17: Operations admin stipend (Simphiwe Msibi) | B17: 3000 | C17: Part-time admin: approvals, verification, support, disputes.
A18: Cloud & hosting (Firebase/Google Cloud) | B18: R500 → R3,000 | C18: Scales with users; usage-based, ramps through the year.
A19: Marketing & community activation | B19: R2,500 → R5,000 | C19: Township activations, field ambassadors, local social ads, print.
A20: Worker onboarding & field ambassadors | B20: 1800 | C20: Getting verified workers onto the platform on the ground.
A21: Legal — Terms/Privacy sign-off + IO registration | B21: 15000 | C21: One-off (M1–M2): attorney review + POPIA Information Officer registration.
A22: Equipment (laptops/phones for field + testing) | B22: 8000 | C22: One-off, Month 1.
A24: Blue cells are inputs you can change. Black numbers on the Cash Flow tab are formulas.

Sheet Cash Flow
A1: Workit (Furthersky Solutions) — 12-Month Cash Flow Projection
A2: All figures in South African Rand (R). Year 1 of operations.
B4: Jul 2026 | C4: Aug 2026 | D4: Sep 2026 | E4: Oct 2026 | F4: Nov 2026 | G4: Dec 2026 | H4: Jan 2027 | I4: Feb 2027 | J4: Mar 2027 | K4: Apr 2027 | L4: May 2027 | M4: Jun 2027 | N4: Total Yr 1
A5: OPENING CASH BALANCE | B5: =Assumptions!B6 -> 5000 | C5: =B29 -> 218000 | D5: =C29 -> 191000 | E5: =D29 -> 174000 | F5: =E29 -> 155800 | G5: =F29 -> 137600 | H5: =G29 -> 118900 | I5: =H29 -> 99400 | J5: =I29 -> 81900 | ... M5: =L29 -> 39400 | N5: =B5 -> 5000
A7: CASH INFLOWS
A8: Grant funding (NYDA / YCF / Pitch & Polish) | B8: =Assumptions!B7 -> 250000 | C8: 0 | D8: 0 | E8: 0 | F8: 0 | G8: 0 | H8: 0 | I8: 0 | J8: 0 | K8: 0 | L8: 0 | M8: 0 | N8: =SUM(B8:M8) -> 250000
A9: Platform revenue (service fees, from M8) | B9: 0 | C9: 0 | D9: 0 | E9: 0 | F9: 0 | G9: 0 | H9: 0 | I9: 2000 | J9: 4000 | K9: 6500 | L9: 9500 | M9: 14500 | N9: =SUM(B9:M9) -> 36500
A10: Total cash inflows | B10: =SUM(B8:B9) -> 250000 | C10: =SUM(C8:C9) -> 0 | D10: =SUM(D8:D9) -> 0 | E10: =SUM(E8:E9) -> 0 | F10: =SUM(F8:F9) -> 0 | G10: =SUM(G8:G9) -> 0 | H10: =SUM(H8:H9) -> 0 | I10: =SUM(I8:I9) -> 2000 | ... M10: =SUM(M8:M9) -> 14500 | N10: =SUM(B10:M10) -> 286500
A12: CASH OUTFLOWS
A13: Founder stipend | B13: 6000 | C13: 6000 | D13: 6000 | E13: 6000 | F13: 6000 | G13: 6000 | H13: 6000 | I13: 6000 | J13: 6000 | K13: 6000 | L13: 6000 | M13: 6000 | N13: =SUM(B13:M13) -> 72000
A14: Operations admin stipend | B14: 3000 | C14: 3000 | D14: 3000 | E14: 3000 | F14: 3000 | G14: 3000 | H14: 3000 | I14: 3000 | J14: 3000 | K14: 3000 | L14: 3000 | M14: 3000 | N14: =SUM(B14:M14) -> 36000
A15: Cloud & hosting (Firebase) | B15: 500 | C15: 500 | D15: 500 | E15: 1200 | F15: 1200 | G15: 1200 | H15: 2000 | I15: 2000 | J15: 2000 | K15: 3000 | L15: 3000 | M15: 3000 | N15: =SUM(B15:M15) -> 20100
A16: Software, domains & tools | B16: 600 | C16: 600 | D16: 600 | E16: 600 | F16: 600 | G16: 600 | H16: 600 | I16: 600 | J16: 600 | K16: 600 | L16: 600 | M16: 600 | N16: =SUM(B16:M16) -> 7200
A17: Communications (WhatsApp/SMS/email) | B17: 300 | C17: 300 | D17: 300 | E17: 300 | F17: 300 | G17: 300 | H17: 300 | I17: 300 | J17: 300 | K17: 300 | L17: 300 | M17: 300 | N17: =SUM(B17:M17) -> 3600
A18: Marketing & community activation | B18: 2500 | C18: 3000 | D18: 3000 | E18: 3500 | F18: 3500 | G18: 4000 | H18: 4000 | I18: 4000 | J18: 4500 | K18: 4500 | L18: 5000 | M18: 5000 | N18: =SUM(B18:M18) -> 46500
A19: Worker onboarding & field ambassadors | B19: 1800 | C19: 1800 | D19: 1800 | E19: 1800 | F19: 1800 | G19: 1800 | H19: 1800 | I19: 1800 | J19: 1800 | K19: 1800 | L19: 1800 | M19: 1800 | N19: =SUM(B19:M19) -> 21600
A20: Transport & field costs | B20: 1000 | C20: 1000 | D20: 1000 | E20: 1000 | F20: 1000 | G20: 1000 | H20: 1000 | I20: 1000 | J20: 1000 | K20: 1000 | L20: 1000 | M20: 1000 | N20: =SUM(B20:M20) -> 12000
A21: Contingency (buffer) | B21: 800 | C21: 800 | D21: 800 | E21: 800 | F21: 800 | G21: 800 | H21: 800 | I21: 800 | J21: 800 | K21: 800 | L21: 800 | M21: 800 | N21: =SUM(B21:M21) -> 9600
A22: Legal — Terms/Privacy + IO registration | B22: 9000 | C22: 6000 | D22: 0 | E22: 0 | F22: 0 | G22: 0 | H22: 0 | I22: 0 | J22: 0 | K22: 0 | L22: 0 | M22: 0 | N22: =SUM(B22:M22) -> 15000
A23: Equipment (laptops/phones) | B23: 8000 | C23: 0 | D23: 0 | E23: 0 | F23: 0 | G23: 0 | H23: 0 | I23: 0 | J23: 0 | K23: 0 | L23: 0 | M23: 0 | N23: =SUM(B23:M23) -> 8000
A24: Accounting & compliance setup | B24: 3500 | C24: 0 | D24: 0 | E24: 0 | F24: 0 | G24: 0 | H24: 0 | I24: 0 | J24: 0 | K24: 0 | L24: 0 | M24: 0 | N24: =SUM(B24:M24) -> 3500
A25: Brand & launch assets | B25: 0 | C25: 4000 | D25: 0 | E25: 0 | F25: 0 | G25: 0 | H25: 0 | I25: 0 | J25: 0 | K25: 0 | L25: 0 | M25: 0 | N25: =SUM(B25:M25) -> 4000
A26: Total cash outflows | B26: =SUM(B13:B25) -> 37000 | C26: =SUM(C13:C25) -> 27000 | D26: =SUM(D13:D25) -> 17000 | E26: =SUM(E13:E25) -> 18200 | F26: =SUM(F13:F25) -> 18200 | G26: =SUM(G13:G25) -> 18700 | H26: =SUM(H13:H25) -> 19500 | I26: =SUM(I13:I25) -> 19500 | ... M26: =SUM(M13:M25) -> 21500 | N26: =SUM(B26:M26) -> 259100
A28: Net cash movement | B28: =B10-B26 -> 213000 | C28: =C10-C26 -> -27000 | D28: =D10-D26 -> -17000 | E28: =E10-E26 -> -18200 | F28: =F10-F26 -> -18200 | G28: =G10-G26 -> -18700 | H28: =H10-H26 -> -19500 | I28: =I10-I26 -> -17500 | ... M28: =M10-M26 -> -7000 | N28: =SUM(B28:M28) -> 27400
A29: CLOSING CASH BALANCE | B29: =B5+B28 -> 218000 | C29: =C5+C28 -> 191000 | D29: =D5+D28 -> 174000 | E29: =E5+E28 -> 155800 | F29: =F5+F28 -> 137600 | G29: =G5+G28 -> 118900 | H29: =H5+H28 -> 99400 | I29: =I5+I28 -> 81900 | ... M29: =M5+M28 -> 32400 | N29: =M29 -> 32400

Sheet Summary
A1: Workit — Year 1 Summary & Use of Funds
A2: Furthersky Solutions · all figures in Rand (R)
A4: FUNDING & REVENUE (Year 1)
A5: Grant funding | B5: ='Cash Flow'!N8 -> 250000
A6: Platform revenue | B6: ='Cash Flow'!N9 -> 36500
A7: Founder seed (opening) | B7: =Assumptions!B6 -> 5000
A8: Total cash available | B8: =B5+B6+B7 -> 291500
A10: USE OF FUNDS — spend by category (Year 1)
A11: People (founder + admin stipends) | B11: ='Cash Flow'!N13+'Cash Flow'!N14 -> 108000 | C11: =B11/$B$17 -> 0.41682748
A12: Infrastructure & tools | B12: =SUM('Cash Flow'!N15:N17) -> 30900 | C12: =B12/$B$17 -> 0.11925897
A13: Marketing & growth | B13: =SUM('Cash Flow'!N18:N19) -> 68100 | C13: =B13/$B$17 -> 0.26283288
A14: Operations (transport, contingency) | B14: =SUM('Cash Flow'!N20:N21) -> 21600 | C14: =B14/$B$17 -> 0.083365496
A15: One-off setup (legal, equipment, brand) | B15: =SUM('Cash Flow'!N22:N25) -> 30500 | C15: =B15/$B$17 -> 0.11771517
A17: Total Year-1 spend | B17: ='Cash Flow'!N26 -> 259100 | C17: =B17/B17 -> 1
A19: KEY METRICS
A20: Year-end cash balance | B20: ='Cash Flow'!M29 -> 32400
A21: Lowest monthly closing balance (runway floor) | B21: =MIN('Cash Flow'!B29:M29) -> 32400
A22: Total operating spend | B22: ='Cash Flow'!N26 -> 259100
A23: Revenue as % of Year-1 spend | B23: ='Cash Flow'!N9/'Cash Flow'!N26 -> 0.14087225
A25: The R250k grant funds a full year of operations with a positive cash buffer at year-end, while platform revenue begins to ramp in the second half.
